Workbook

Sheet Raw Data
A1: Order_ID | B1: Product_Category | C1: Product_Name | D1: Units_Sold | E1: Price_Per_Unit | F1: Discount_% | G1: Shipping_Cost | H1: Total_Revenue | I1: Order_Date | J1: Customer_City | K1: Payment_Status | L1: Note
A2: ORD001 | B2: Laptop | C2: Dell Inspiron 15 | D2: 1 | E2: 55000 | F2: 0.1 | G2: 500 | H2: 49500 | I2: 46027 | J2: Mumbai | K2: Paid
A3: ORD002 | B3: Phone | C3: iPhone 14 | D3: 2 | E3: 79000 | F3: 0.05 | G3: 0 | H3: 150100 | I3: 46030 | J3: Delhi | K3: Paid
A4: ORD003 | B4: Tablet | C4: iPad Air | D4: 1 | E4: 60000 | F4: 0.15 | G4: 300 | H4: 51300 | I4: 46034 | J4: Bangalore | K4: Paid
A5: ORD004 | B5: Headphones | C5: Sony WH-1000XM5 | D5: 3 | E5: 29000 | F5: 0.2 | G5: 200 | H5: 69800 | I5: 46037 | J5: Mumbai | K5: Paid
A6: ORD005 | B6: Laptop | C6: MacBook Air M2 | D6: 1 | E6: 115000 | F6: 0.05 | G6: free | H6: 109250 | I6: 46040 | J6: Pune | K6: Paid | L6: shipping cost is free mabye it is 0 like other
A7: ORD006 | B7: Phone | C7: Samsung S23 | D7: 2 | E7: 65000 | F7: 0.25 | G7: 400 | H7: 97900 | I7: 46044 | J7: Delhi | K7: Pending
A8: ORD007 | B8: Smartwatch | C8: Apple Watch 9 | D8: 5 | E8: 45000 | F8: 0.3 | G8: 0 | H8: 157500 | I8: 46047 | J8: Chennai | K8: Paid
A9: ORD008 | B9: Tablet | C9: Samsung Tab S9 | D9: 0 | E9: 48000 | F9: 0.1 | G9: 250 | H9: 0 | I9: 46050 | J9: Kolkata | K9: Cancelled | L9: Unit sold is 0 but shipping cost occurs and cancelled order
A10: ORD009 | B10: Laptop | C10: HP Pavilion | D10: 1 | E10: 52000 | F10: 0.05 | G10: 600 | H10: 49400 | I10: 46055 | J10: Mumbai | K10: Paid
A11: ORD010 | B11: Headphones | C11: Bose QC45 | D11: -1 | E11: 28000 | F11: 0 | G11: 150 | H11: -28000 | I11: 46058 | J11: Hyderabad | K11: Return | L11: Negative Unitsold & negative unitsold and Return order
A12: ORD011 | B12: Phone | C12: OnePlus 11 | D12: 2 | E12: 56000 | F12: 0.15 | G12: 0 | H12: 95200 | I12: 46061 | J12: Bangalore | K12: Paid
A13: ORD012 | B13: Laptop | C13: Dell XPS 13 | D13: 1 | E13: 125000 | F13: 0.1 | G13: 500 | H13: 112500 | I13: 46065 | J13: Mumbai | K13: Paid
A14: ORD013 | B14: Smartwatch | C14: Fitbit Versa 4 | D14: 3 | E14: 22000 | F14: 0.05 | G14: 200 | H14: 62900 | I14: 46068 | J14: Chennai | K14: paid
A15: ORD014 | B15: Tablet | C15: iPad Pro 12.9 | D15: 1 | E15: 110000 | F15: 0.08 | H15: 101200 | I15: 46071 | J15: Delhi | K15: Paid | L15: Blank Shipping cost
A16: ORD015 | B16: Phone | C16: Xiaomi 13 Pro | D16: 4 | E16: 59000 | F16: 0.4 | G16: 0 | H16: 141600 | I16: 46075 | J16: Pune | K16: Paid
A17: ORD016 | B17: Laptop | C17: ASUS ROG | D17: 1 | E17: 135000 | F17: 0.12 | G17: 700 | H17: 118800 | I17: 46078 | J17: Kolkata | K17: Paid
A18: ORD017 | B18: Headphones | C18: JBL Tune 510 | D18: 10 | E18: 3500 | F18: 0 | G18: 100 | H18: 35100 | I18: 46081 | J18: Mumbai | K18: Paid
A19: ORD018 | B19: Phone | C19: iPhone 15 Pro | D19: 1 | E19: 145000 | F19: 0.03 | G19: 0 | H19: 140650 | I19: 46086 | J19: Bangalore | K19: Paid
A20: ORD019 | B20: Laptop | C20: Lenovo ThinkPad | D20: 2 | E20: 85000 | F20: 0.08 | G20: 500 | H20: 156400 | I20: 46091 | J20: Delhi | K20: Paid
A21: ORD020 | B21: Smartwatch | C21: Garmin Fenix 7 | D21: 2 | E21: 75000 | F21: 0.15 | G21: 300 | H21: 127800 | I21: 46096 | J21: Chennai | K21: Pending
A22: ORD021 | B22: Tablet | C22: Lenovo Tab P11 | D22: 3 | E22: 28000 | F22: 0.1 | G22: 0 | H22: 75600 | I22: 46101 | J22: Mumbai | K22: Paid
A23: ORD022 | B23: Phone | C23: Google Pixel 8 | D23: 1 | E23: 72000 | F23: 0.05 | G23: 200 | H23: 68600 | I23: 46106 | J23: Hyderabad | K23: Paid
A24: ORD023 | B24: Laptop | C24: Acer Aspire 5 | D24: 1 | E24: 45000 | F24: 0 | G24: 400 | H24: 45400 | I24: 46109 | J24: Pune | K24: Paid

Sheet Error log
A1: Error# | B1: RowField | C1: Original | D1: Problem | E1: Correction | F1: Reason | G1: Confidence | L1: Note
A2: 1 | B2: All Row of First Three column | D2: Not Direct problem but Name are incocsistent | E2: Use Proper(trim) function for correction | F2: Name must be always Capital | G2: 10
A3: 2 | B3: ORD008 | C3: Zero unit sold and 0 revenue | D3: In sales data transrlation is 0 | E3: change to 0 | F3: In status there is written is cancelled so canclelled means not anythings happened so all things must be 0 | G3: 10
A4: 3 | B4: ORD008 | C4: Shipping cost is 250 | D4: status is cancelled | E4: shipping cost must be 0 | F4: with out any transcation shipping cost can not be orrurred | G4: 10
A5: 4 | B5: ORD010 | C5: Negative quantity and Revenue | D5: Negative amont | E5: Leave it as a negative | F5: In status this roder is returned and return reduce Revenue | G5: 10
A6: 5 | B6: ORD005 | C6: shipping cost is Free | D6: Shipping cost is amont column and it says free( a text) is effect to data | E6: chagne free to 0 | F6: amount column always must be in number value | G6: 10
A7: 6 | B7: ORD014 | C7: Shipping cost is blank | D7: No any text or amount to what actually it is | E7: take it as a 0 | F7: Shipping cost is blank and I did not assume by other relative pattern because it is blank and I consider it as a Free or 0 | G7: 7
A8: 7 | B8: All row of Customercity | C8: text column | D8: mabye somewhere text written mistake | E8: Use Proper(trim) function | F8: For text column correction | G8: 10
A9: 8 | B9: All row of Payment status | C9: text column | D9: Text incosistence | E9: Use Proper(trim) function | F9: for data correctness | G9: 8

Sheet Clean data
A1: Order_Id | B1: Product_Category | C1: Product_Name | D1: Units_Sold | E1: Price_Per_Unit | F1: Discount_% | G1: Shipping_Cost | H1: Total_Revenue | I1: Order_Date | J1: Customer_City | K1: Payment_Status | L1: Note
A2: ORD001 | B2: Laptop | C2: Dell Inspiron 15 | D2: 1 | E2: 55000 | F2: 0.1 | G2: 500 | H2: 50000 | I2: 46027 | J2: Mumbai | K2: Paid
A3: ORD002 | B3: Phone | C3: Iphone 14 | D3: 2 | E3: 79000 | F3: 0.05 | G3: 0 | H3: 150100 | I3: 46030 | J3: Delhi | K3: Paid
A4: ORD003 | B4: Tablet | C4: Ipad Air | D4: 1 | E4: 60000 | F4: 0.15 | G4: 300 | H4: 51300 | I4: 46034 | J4: Bangalore | K4: Paid
A5: ORD004 | B5: Headphones | C5: Sony Wh-1000Xm5 | D5: 3 | E5: 29000 | F5: 0.2 | G5: 200 | H5: 69800 | I5: 46037 | J5: Mumbai | K5: Paid | L5: Discount is greater then 20% it effect to busines
A6: ORD005 | B6: Laptop | C6: Macbook Air M2 | D6: 1 | E6: 115000 | F6: 0.05 | G6: 0 | H6: 109250 | I6: 46040 | J6: Pune | K6: Paid
A7: ORD006 | B7: Phone | C7: Samsung S23 | D7: 2 | E7: 65000 | F7: 0.25 | G7: 400 | H7: 97900 | I7: 46044 | J7: Delhi | K7: Pending | L7: Discount is greater then 20% it effect to busines
A8: ORD007 | B8: Smartwatch | C8: Apple Watch 9 | D8: 5 | E8: 45000 | F8: 0.3 | G8: 0 | H8: 157500 | I8: 46047 | J8: Chennai | K8: Paid | L8: Discount is greater then 20% it effect to busines
A9: ORD008 | B9: Tablet | C9: Samsung Tab S9 | D9: 0 | E9: 48000 | F9: 0.1 | G9: 0 | H9: 0 | I9: 46050 | J9: Kolkata | K9: Cancelled | L9: change shipping cost to zero amount.
A10: ORD009 | B10: Laptop | C10: Hp Pavilion | D10: 1 | E10: 52000 | F10: 0.05 | G10: 600 | H10: 50000 | I10: 46055 | J10: Mumbai | K10: Paid
A11: ORD010 | B11: Headphones | C11: Bose Qc45 | D11: -1 | E11: 28000 | F11: 0 | G11: 150 | H11: -27850 | I11: 46058 | J11: Hyderabad | K11: Return | L11: shipping cost is Return or not because sometimes if goods are return due to business then everythings return even shippipng cost or delivary cost. (Please verify)
A12: ORD011 | B12: Phone | C12: Oneplus 11 | D12: 2 | E12: 56000 | F12: 0.15 | G12: 0 | H12: 95200 | I12: 46061 | J12: Bangalore | K12: Paid
A13: ORD012 | B13: Laptop | C13: Dell Xps 13 | D13: 1 | E13: 125000 | F13: 0.1 | G13: 500 | H13: 113000 | I13: 46065 | J13: Mumbai | K13: Paid
A14: ORD013 | B14: Smartwatch | C14: Fitbit Versa 4 | D14: 3 | E14: 22000 | F14: 0.05 | G14: 200 | H14: 62900 | I14: 46068 | J14: Chennai | K14: Paid
A15: ORD014 | B15: Tablet | C15: Ipad Pro 12.9 | D15: 1 | E15: 110000 | F15: 0.08 | G15: 0 | H15: 101200 | I15: 46071 | J15: Delhi | K15: Paid
A16: ORD015 | B16: Phone | C16: Xiaomi 13 Pro | D16: 4 | E16: 59000 | F16: 0.4 | G16: 0 | H16: 141600 | I16: 46075 | J16: Pune | K16: Paid | L16: Discount is greater then 35% it effect to busines
A17: ORD016 | B17: Laptop | C17: Asus Rog | D17: 1 | E17: 135000 | F17: 0.12 | G17: 700 | H17: 119500 | I17: 46078 | J17: Kolkata | K17: Paid
A18: ORD017 | B18: Headphones | C18: Jbl Tune 510 | D18: 10 | E18: 3500 | F18: 0 | G18: 100 | H18: 35100 | I18: 46081 | J18: Mumbai | K18: Paid
A19: ORD018 | B19: Phone | C19: Iphone 15 Pro | D19: 1 | E19: 145000 | F19: 0.03 | G19: 0 | H19: 140650 | I19: 46086 | J19: Bangalore | K19: Paid
A20: ORD019 | B20: Laptop | C20: Lenovo Thinkpad | D20: 2 | E20: 85000 | F20: 0.08 | G20: 500 | H20: 156900 | I20: 46091 | J20: Delhi | K20: Paid
A21: ORD020 | B21: Smartwatch | C21: Garmin Fenix 7 | D21: 2 | E21: 75000 | F21: 0.15 | G21: 300 | H21: 127800 | I21: 46096 | J21: Chennai | K21: Pending
A22: ORD021 | B22: Tablet | C22: Lenovo Tab P11 | D22: 3 | E22: 28000 | F22: 0.1 | G22: 0 | H22: 75600 | I22: 46101 | J22: Mumbai | K22: Paid
A23: ORD022 | B23: Phone | C23: Google Pixel 8 | D23: 1 | E23: 72000 | F23: 0.05 | G23: 200 | H23: 68600 | I23: 46106 | J23: Hyderabad | K23: Paid
A24: ORD023 | B24: Laptop | C24: Acer Aspire 5 | D24: 1 | E24: 45000 | F24: 0 | G24: 400 | H24: 45400 | I24: 46109 | J24: Pune | K24: Paid

Sheet Sales Anylsis
A1: Description | B1: Amount
A2: Total Revenue | B2: =SUM('Clean data'!H2:H24) -> 1991450
A3: Total Shipping Cost | B3: =SUM('Clean data'!G2:G24) -> 5050
A4: Total Quantity sold | B4: =SUM('Clean data'!D2:D24) -> 47
A8: Category Details | B8: Revenue | C8: % of Revenue
A9: Phone | B9: 694050 | C9: 34.85149
A10: Laptop | B10: 644050 | C10: 32.340757
A11: Smartwatch | B11: 348200 | C11: 17.484747
A12: Tablet | B12: 228100 | C12: 11.453966
A13: Headphones | B13: 77050 | C13: 3.8690401
A14: Total | B14: =SUM(B9:B13) -> 1991450 | C14: =SUM(C9:C13) -> 100
A16: City Details | B16: Revenue | C16: % of Revenue
A17: ='Clean data'!J2 -> Mumbai | B17: =SUMIF('Clean data'!$J$2:$J$24,'Sales Anylsis'!A17,'Clean data'!$H$2:$H$24) -> 393500 | C17: =B17/$B$24*100 -> 19.759472
A18: ='Clean data'!J3 -> Delhi | B18: =SUMIF('Clean data'!$J$2:$J$24,'Sales Anylsis'!A18,'Clean data'!$H$2:$H$24) -> 506100 | C18: =B18/$B$24*100 -> 25.413643
A19: ='Clean data'!J4 -> Bangalore | B19: =SUMIF('Clean data'!$J$2:$J$24,'Sales Anylsis'!A19,'Clean data'!$H$2:$H$24) -> 287150 | C19: =B19/$B$24*100 -> 14.419142
A20: ='Clean data'!J6 -> Pune | B20: =SUMIF('Clean data'!$J$2:$J$24,'Sales Anylsis'!A20,'Clean data'!$H$2:$H$24) -> 296250 | C20: =B20/$B$24*100 -> 14.876095
A21: ='Clean data'!J8 -> Chennai | B21: =SUMIF('Clean data'!$J$2:$J$24,'Sales Anylsis'!A21,'Clean data'!$H$2:$H$24) -> 348200 | C21: =B21/$B$24*100 -> 17.484747
A22: ='Clean data'!J9 -> Kolkata | B22: =SUMIF('Clean data'!$J$2:$J$24,'Sales Anylsis'!A22,'Clean data'!$H$2:$H$24) -> 119500 | C22: =B22/$B$24*100 -> 6.0006528
A23: ='Clean data'!J11 -> Hyderabad | B23: =SUMIF('Clean data'!$J$2:$J$24,'Sales Anylsis'!A23,'Clean data'!$H$2:$H$24) -> 40750 | C23: =B23/$B$24*100 -> 2.0462477
A24: Total | B24: =SUM(B17:B23) -> 1991450 | C24: =SUM(C17:C23) -> 100
A26: Discount Average | B26: =AVERAGE('Clean data'!F2:F24)*100 -> 11.130435

Sheet Profit anylsis
A1: ='Clean data'!A1 -> Order_Id | B1: Actual Sales | C1: Actual Discount | D1: Actual Return | E1: Net sales | F1: Cogs(Cost produtct) | G1: Gross Profit | H1: Other Expenses(Payment getway fee) | I1: Other Income(shipping cost) | J1: Net Profit
A2: ='Clean data'!A2 -> ORD001 | B2: =ABS('Clean data'!D2*'Clean data'!E2) -> 55000 | C2: =ABS(('Clean data'!D2*'Clean data'!E2)*'Clean data'!F2) -> 5500 | D2: =IF('Clean data'!K2="Return",ABS('Clean data'!D2*'Clean data'!E2),0) -> 0 | E2: =B2-C2-D2 -> 49500 | F2: =ABS('Clean data'!D2*('Clean data'!E2*0.7)) -> 38500 | G2: =E2-F2 -> 11000 | H2: =IF('Clean data'!K2="Paid",'Clean data'!H2*0.02,0) -> 1000 | I2: ='Clean data'!G2 -> 500 | J2: =G2-H2+I2 -> 10500
A3: ='Clean data'!A3 -> ORD002 | B3: =ABS('Clean data'!D3*'Clean data'!E3) -> 158000 | C3: =ABS(('Clean data'!D3*'Clean data'!E3)*'Clean data'!F3) -> 7900 | D3: =IF('Clean data'!K3="Return",ABS('Clean data'!D3*'Clean data'!E3),0) -> 0 | E3: =B3-C3-D3 -> 150100 | F3: =ABS('Clean data'!D3*('Clean data'!E3*0.7)) -> 110600 | G3: =E3-F3 -> 39500 | H3: =IF('Clean data'!K3="Paid",'Clean data'!H3*0.02,0) -> 3002 | I3: ='Clean data'!G3 -> 0 | J3: =G3-H3+I3 -> 36498 | K3: Total Sales | L3: =B25 -> 2395000
A4: ='Clean data'!A4 -> ORD003 | B4: =ABS('Clean data'!D4*'Clean data'!E4) -> 60000 | C4: =ABS(('Clean data'!D4*'Clean data'!E4)*'Clean data'!F4) -> 9000 | D4: =IF('Clean data'!K4="Return",ABS('Clean data'!D4*'Clean data'!E4),0) -> 0 | E4: =B4-C4-D4 -> 51000 | F4: =ABS('Clean data'!D4*('Clean data'!E4*0.7)) -> 42000 | G4: =E4-F4 -> 9000 | H4: =IF('Clean data'!K4="Paid",'Clean data'!H4*0.02,0) -> 1026 | I4: ='Clean data'!G4 -> 300 | J4: =G4-H4+I4 -> 8274 | K4: Total Discount | L4: =C25 -> 352600
A5: ='Clean data'!A5 -> ORD004 | B5: =ABS('Clean data'!D5*'Clean data'!E5) -> 87000 | C5: =ABS(('Clean data'!D5*'Clean data'!E5)*'Clean data'!F5) -> 17400 | D5: =IF('Clean data'!K5="Return",ABS('Clean data'!D5*'Clean data'!E5),0) -> 0 | E5: =B5-C5-D5 -> 69600 | F5: =ABS('Clean data'!D5*('Clean data'!E5*0.7)) -> 60900 | G5: =E5-F5 -> 8700 | H5: =IF('Clean data'!K5="Paid",'Clean data'!H5*0.02,0) -> 1396 | I5: ='Clean data'!G5 -> 200 | J5: =G5-H5+I5 -> 7504 | K5: Total Return | L5: =D25 -> 28000
A6: ='Clean data'!A6 -> ORD005 | B6: =ABS('Clean data'!D6*'Clean data'!E6) -> 115000 | C6: =ABS(('Clean data'!D6*'Clean data'!E6)*'Clean data'!F6) -> 5750 | D6: =IF('Clean data'!K6="Return",ABS('Clean data'!D6*'Clean data'!E6),0) -> 0 | E6: =B6-C6-D6 -> 109250 | F6: =ABS('Clean data'!D6*('Clean data'!E6*0.7)) -> 80500 | G6: =E6-F6 -> 28750 | H6: =IF('Clean data'!K6="Paid",'Clean data'!H6*0.02,0) -> 2185 | I6: ='Clean data'!G6 -> 0 | J6: =G6-H6+I6 -> 26565 | K6: Net Sales | L6: =L3-L4-L5 -> 2014400
A7: ='Clean data'!A7 -> ORD006 | B7: =ABS('Clean data'!D7*'Clean data'!E7) -> 130000 | C7: =ABS(('Clean data'!D7*'Clean data'!E7)*'Clean data'!F7) -> 32500 | D7: =IF('Clean data'!K7="Return",ABS('Clean data'!D7*'Clean data'!E7),0) -> 0 | E7: =B7-C7-D7 -> 97500 | F7: =ABS('Clean data'!D7*('Clean data'!E7*0.7)) -> 91000 | G7: =E7-F7 -> 6500 | H7: =IF('Clean data'!K7="Paid",'Clean data'!H7*0.02,0) -> 0 | I7: ='Clean data'!G7 -> 400 | J7: =G7-H7+I7 -> 6900 | K7: Cogs(Cost Product) | L7: =F25 -> 1676500
A8: ='Clean data'!A8 -> ORD007 | B8: =ABS('Clean data'!D8*'Clean data'!E8) -> 225000 | C8: =ABS(('Clean data'!D8*'Clean data'!E8)*'Clean data'!F8) -> 67500 | D8: =IF('Clean data'!K8="Return",ABS('Clean data'!D8*'Clean data'!E8),0) -> 0 | E8: =B8-C8-D8 -> 157500 | F8: =ABS('Clean data'!D8*('Clean data'!E8*0.7)) -> 157500 | G8: =E8-F8 -> 0 | H8: =IF('Clean data'!K8="Paid",'Clean data'!H8*0.02,0) -> 3150 | I8: ='Clean data'!G8 -> 0 | J8: =G8-H8+I8 -> -3150 | K8: Gross Profit | L8: =L6-L7 -> 337900
A9: ='Clean data'!A9 -> ORD008 | B9: =ABS('Clean data'!D9*'Clean data'!E9) -> 0 | C9: =ABS(('Clean data'!D9*'Clean data'!E9)*'Clean data'!F9) -> 0 | D9: =IF('Clean data'!K9="Return",ABS('Clean data'!D9*'Clean data'!E9),0) -> 0 | E9: =B9-C9-D9 -> 0 | F9: =ABS('Clean data'!D9*('Clean data'!E9*0.7)) -> 0 | G9: =E9-F9 -> 0 | H9: =IF('Clean data'!K9="Paid",'Clean data'!H9*0.02,0) -> 0 | I9: ='Clean data'!G9 -> 0 | J9: =G9-H9+I9 -> 0 | K9: Other Expenses(payment getway fee) | L9: =H25 -> 35872
A10: ='Clean data'!A10 -> ORD009 | B10: =ABS('Clean data'!D10*'Clean data'!E10) -> 52000 | C10: =ABS(('Clean data'!D10*'Clean data'!E10)*'Clean data'!F10) -> 2600 | D10: =IF('Clean data'!K10="Return",ABS('Clean data'!D10*'Clean data'!E10),0) -> 0 | E10: =B10-C10-D10 -> 49400 | F10: =ABS('Clean data'!D10*('Clean data'!E10*0.7)) -> 36400 | G10: =E10-F10 -> 13000 | H10: =IF('Clean data'!K10="Paid",'Clean data'!H10*0.02,0) -> 1000 | I10: ='Clean data'!G10 -> 600 | J10: =G10-H10+I10 -> 12600 | K10: Other income | L10: =I25 -> 5050
A11: ='Clean data'!A11 -> ORD010 | B11: =ABS('Clean data'!D11*'Clean data'!E11) -> 28000 | C11: =ABS(('Clean data'!D11*'Clean data'!E11)*'Clean data'!F11) -> 0 | D11: =IF('Clean data'!K11="Return",ABS('Clean data'!D11*'Clean data'!E11),0) -> 28000 | E11: =B11-C11-D11 -> 0 | F11: =ABS('Clean data'!D11*('Clean data'!E11*0.7)) -> 19600 | G11: =E11-F11 -> -19600 | H11: =IF('Clean data'!K11="Paid",'Clean data'!H11*0.02,0) -> 0 | I11: ='Clean data'!G11 -> 150 | J11: =G11-H11+I11 -> -19450 | K11: Net Profit | L11: =L8-L9+L10 -> 307078
A12: ='Clean data'!A12 -> ORD011 | B12: =ABS('Clean data'!D12*'Clean data'!E12) -> 112000 | C12: =ABS(('Clean data'!D12*'Clean data'!E12)*'Clean data'!F12) -> 16800 | D12: =IF('Clean data'!K12="Return",ABS('Clean data'!D12*'Clean data'!E12),0) -> 0 | E12: =B12-C12-D12 -> 95200 | F12: =ABS('Clean data'!D12*('Clean data'!E12*0.7)) -> 78400 | G12: =E12-F12 -> 16800 | H12: =IF('Clean data'!K12="Paid",'Clean data'!H12*0.02,0) -> 1904 | I12: ='Clean data'!G12 -> 0 | J12: =G12-H12+I12 -> 14896 | K12: Net Profit margin | L12: =L11/L6 -> 0.15244142
A13: ='Clean data'!A13 -> ORD012 | B13: =ABS('Clean data'!D13*'Clean data'!E13) -> 125000 | C13: =ABS(('Clean data'!D13*'Clean data'!E13)*'Clean data'!F13) -> 12500 | D13: =IF('Clean data'!K13="Return",ABS('Clean data'!D13*'Clean data'!E13),0) -> 0 | E13: =B13-C13-D13 -> 112500 | F13: =ABS('Clean data'!D13*('Clean data'!E13*0.7)) -> 87500 | G13: =E13-F13 -> 25000 | H13: =IF('Clean data'!K13="Paid",'Clean data'!H13*0.02,0) -> 2260 | I13: ='Clean data'!G13 -> 500 | J13: =G13-H13+I13 -> 23240 | K13: Gross profit margin | L13: =L8/L6 -> 0.16774226
A14: ='Clean data'!A14 -> ORD013 | B14: =ABS('Clean data'!D14*'Clean data'!E14) -> 66000 | C14: =ABS(('Clean data'!D14*'Clean data'!E14)*'Clean data'!F14) -> 3300 | D14: =IF('Clean data'!K14="Return",ABS('Clean data'!D14*'Clean data'!E14),0) -> 0 | E14: =B14-C14-D14 -> 62700 | F14: =ABS('Clean data'!D14*('Clean data'!E14*0.7)) -> 46200 | G14: =E14-F14 -> 16500 | H14: =IF('Clean data'!K14="Paid",'Clean data'!H14*0.02,0) -> 1258 | I14: ='Clean data'!G14 -> 200 | J14: =G14-H14+I14 -> 15442
A15: ='Clean data'!A15 -> ORD014 | B15: =ABS('Clean data'!D15*'Clean data'!E15) -> 110000 | C15: =ABS(('Clean data'!D15*'Clean data'!E15)*'Clean data'!F15) -> 8800 | D15: =IF('Clean data'!K15="Return",ABS('Clean data'!D15*'Clean data'!E15),0) -> 0 | E15: =B15-C15-D15 -> 101200 | F15: =ABS('Clean data'!D15*('Clean data'!E15*0.7)) -> 77000 | G15: =E15-F15 -> 24200 | H15: =IF('Clean data'!K15="Paid",'Clean data'!H15*0.02,0) -> 2024 | I15: ='Clean data'!G15 -> 0 | J15: =G15-H15+I15 -> 22176
A16: ='Clean data'!A16 -> ORD015 | B16: =ABS('Clean data'!D16*'Clean data'!E16) -> 236000 | C16: =ABS(('Clean data'!D16*'Clean data'!E16)*'Clean data'!F16) -> 94400 | D16: =IF('Clean data'!K16="Return",ABS('Clean data'!D16*'Clean data'!E16),0) -> 0 | E16: =B16-C16-D16 -> 141600 | F16: =ABS('Clean data'!D16*('Clean data'!E16*0.7)) -> 165200 | G16: =E16-F16 -> -23600 | H16: =IF('Clean data'!K16="Paid",'Clean data'!H16*0.02,0) -> 2832 | I16: ='Clean data'!G16 -> 0 | J16: =G16-H16+I16 -> -26432
A17: ='Clean data'!A17 -> ORD016 | B17: =ABS('Clean data'!D17*'Clean data'!E17) -> 135000 | C17: =ABS(('Clean data'!D17*'Clean data'!E17)*'Clean data'!F17) -> 16200 | D17: =IF('Clean data'!K17="Return",ABS('Clean data'!D17*'Clean data'!E17),0) -> 0 | E17: =B17-C17-D17 -> 118800 | F17: =ABS('Clean data'!D17*('Clean data'!E17*0.7)) -> 94500 | G17: =E17-F17 -> 24300 | H17: =IF('Clean data'!K17="Paid",'Clean data'!H17*0.02,0) -> 2390 | I17: ='Clean data'!G17 -> 700 | J17: =G17-H17+I17 -> 22610
A18: ='Clean data'!A18 -> ORD017 | B18: =ABS('Clean data'!D18*'Clean data'!E18) -> 35000 | C18: =ABS(('Clean data'!D18*'Clean data'!E18)*'Clean data'!F18) -> 0 | D18: =IF('Clean data'!K18="Return",ABS('Clean data'!D18*'Clean data'!E18),0) -> 0 | E18: =B18-C18-D18 -> 35000 | F18: =ABS('Clean data'!D18*('Clean data'!E18*0.7)) -> 24500 | G18: =E18-F18 -> 10500 | H18: =IF('Clean data'!K18="Paid",'Clean data'!H18*0.02,0) -> 702 | I18: ='Clean data'!G18 -> 100 | J18: =G18-H18+I18 -> 9898
A19: ='Clean data'!A19 -> ORD018 | B19: =ABS('Clean data'!D19*'Clean data'!E19) -> 145000 | C19: =ABS(('Clean data'!D19*'Clean data'!E19)*'Clean data'!F19) -> 4350 | D19: =IF('Clean data'!K19="Return",ABS('Clean data'!D19*'Clean data'!E19),0) -> 0 | E19: =B19-C19-D19 -> 140650 | F19: =ABS('Clean data'!D19*('Clean data'!E19*0.7)) -> 101500 | G19: =E19-F19 -> 39150 | H19: =IF('Clean data'!K19="Paid",'Clean data'!H19*0.02,0) -> 2813 | I19: ='Clean data'!G19 -> 0 | J19: =G19-H19+I19 -> 36337
A20: ='Clean data'!A20 -> ORD019 | B20: =ABS('Clean data'!D20*'Clean data'!E20) -> 170000 | C20: =ABS(('Clean data'!D20*'Clean data'!E20)*'Clean data'!F20) -> 13600 | D20: =IF('Clean data'!K20="Return",ABS('Clean data'!D20*'Clean data'!E20),0) -> 0 | E20: =B20-C20-D20 -> 156400 | F20: =ABS('Clean data'!D20*('Clean data'!E20*0.7)) -> 119000 | G20: =E20-F20 -> 37400 | H20: =IF('Clean data'!K20="Paid",'Clean data'!H20*0.02,0) -> 3138 | I20: ='Clean data'!G20 -> 500 | J20: =G20-H20+I20 -> 34762
A21: ='Clean data'!A21 -> ORD020 | B21: =ABS('Clean data'!D21*'Clean data'!E21) -> 150000 | C21: =ABS(('Clean data'!D21*'Clean data'!E21)*'Clean data'!F21) -> 22500 | D21: =IF('Clean data'!K21="Return",ABS('Clean data'!D21*'Clean data'!E21),0) -> 0 | E21: =B21-C21-D21 -> 127500 | F21: =ABS('Clean data'!D21*('Clean data'!E21*0.7)) -> 105000 | G21: =E21-F21 -> 22500 | H21: =IF('Clean data'!K21="Paid",'Clean data'!H21*0.02,0) -> 0 | I21: ='Clean data'!G21 -> 300 | J21: =G21-H21+I21 -> 22800
A22: ='Clean data'!A22 -> ORD021 | B22: =ABS('Clean data'!D22*'Clean data'!E22) -> 84000 | C22: =ABS(('Clean data'!D22*'Clean data'!E22)*'Clean data'!F22) -> 8400 | D22: =IF('Clean data'!K22="Return",ABS('Clean data'!D22*'Clean data'!E22),0) -> 0 | E22: =B22-C22-D22 -> 75600 | F22: =ABS('Clean data'!D22*('Clean data'!E22*0.7)) -> 58800 | G22: =E22-F22 -> 16800 | H22: =IF('Clean data'!K22="Paid",'Clean data'!H22*0.02,0) -> 1512 | I22: ='Clean data'!G22 -> 0 | J22: =G22-H22+I22 -> 15288
A23: ='Clean data'!A23 -> ORD022 | B23: =ABS('Clean data'!D23*'Clean data'!E23) -> 72000 | C23: =ABS(('Clean data'!D23*'Clean data'!E23)*'Clean data'!F23) -> 3600 | D23: =IF('Clean data'!K23="Return",ABS('Clean data'!D23*'Clean data'!E23),0) -> 0 | E23: =B23-C23-D23 -> 68400 | F23: =ABS('Clean data'!D23*('Clean data'!E23*0.7)) -> 50400 | G23: =E23-F23 -> 18000 | H23: =IF('Clean data'!K23="Paid",'Clean data'!H23*0.02,0) -> 1372 | I23: ='Clean data'!G23 -> 200 | J23: =G23-H23+I23 -> 16828
A24: ='Clean data'!A24 -> ORD023 | B24: =ABS('Clean data'!D24*'Clean data'!E24) -> 45000 | C24: =ABS(('Clean data'!D24*'Clean data'!E24)*'Clean data'!F24) -> 0 | D24: =IF('Clean data'!K24="Return",ABS('Clean data'!D24*'Clean data'!E24),0) -> 0 | E24: =B24-C24-D24 -> 45000 | F24: =ABS('Clean data'!D24*('Clean data'!E24*0.7)) -> 31500 | G24: =E24-F24 -> 13500 | H24: =IF('Clean data'!K24="Paid",'Clean data'!H24*0.02,0) -> 908 | I24: ='Clean data'!G24 -> 400 | J24: =G24-H24+I24 -> 12992
A25: Total | B25: =SUM(B2:B24) -> 2395000 | C25: =SUM(C2:C24) -> 352600 | D25: =SUM(D2:D24) -> 28000 | E25: =SUM(E2:E24) -> 2014400 | F25: =SUM(F2:F24) -> 1676500 | G25: =SUM(G2:G24) -> 337900 | H25: =SUM(H2:H24) -> 35872 | I25: =SUM(I2:I24) -> 5050 | J25: =SUM(J2:J24) -> 307078
